cmakeperf/__init__.py
cmakeperf/cli.py
cmakeperf-0.6.0.dist-info/METADATA
cmakeperf-0.6.0.dist-info/WHEEL
cmakeperf-0.6.0.dist-info/entry_points.txt
cmakeperf-0.6.0.dist-info/RECORD
